deeptracy_core/__init__.py
deeptracy_core/config.py
deeptracy_core/decorator.py
deeptracy_core/docker_helpers.py
deeptracy_core/utils.py
deeptracy_core/dal/__init__.py
deeptracy_core/dal/database.py
deeptracy_core/dal/project/__init__.py
deeptracy_core/dal/project/manager.py
deeptracy_core/dal/project/model.py
deeptracy_core/dal/project/project_hooks.py
deeptracy_core/dal/project/repo_auth.py
deeptracy_core/dal/scan/__init__.py
deeptracy_core/dal/scan/manager.py
deeptracy_core/dal/scan/model.py
deeptracy_core/dal/scan_dep/__init__.py
deeptracy_core/dal/scan_dep/manager.py
deeptracy_core/dal/scan_dep/model.py
deeptracy_core/dal/scan_vul/__init__.py
deeptracy_core/dal/scan_vul/manager.py
deeptracy_core/dal/scan_vul/model.py
deeptracy_core/dal/vulnerability/__init__.py
deeptracy_core/dal/vulnerability/manager.py
deeptracy_core/dal/vulnerability/models.py
deeptracy_core-0.0.34.dist-info/DESCRIPTION.rst
deeptracy_core-0.0.34.dist-info/METADATA
deeptracy_core-0.0.34.dist-info/RECORD
deeptracy_core-0.0.34.dist-info/WHEEL
deeptracy_core-0.0.34.dist-info/metadata.json
deeptracy_core-0.0.34.dist-info/top_level.txt
tests/__init__.py
tests/unit/__init__.py
tests/unit/base_test.py
tests/unit/mock_db.py
tests/unit/test_docker_helpers.py
tests/unit/dal/__init__.py
tests/unit/dal/test_database.py
tests/unit/dal/test_project_manager.py
tests/unit/dal/test_scan_dep_manager.py
tests/unit/dal/test_scan_manager.py
tests/unit/dal/test_scan_vul_manager.py
