Metadata-Version: 2.0
Name: deeptracy-core
Version: 0.0.34
Summary: Deeptracy Dependency Checker
Home-page: https://github.com/BBVA/deeptracy-core
Author: BBVA
Author-email: UNKNOWN
License: UNKNOWN
Keywords: deeptracy core
Platform: UNKNOWN
Classifier: Programming Language :: Python :: 3.6
Classifier: Topic :: Software Development :: Libraries :: Python Modules
Requires-Dist: docker (==2.5.1)
Requires-Dist: SQLAlchemy (==1.1.14)
Requires-Dist: SQLAlchemy-Utils (==0.32.16)
